LICENSE
MANIFEST.in
README.rst
setup.cfg
setup.py
versioneer.py
tpDcc/__init__.py
tpDcc/libs/__init__.py
tpDcc/libs/datalibrary/__init__.py
tpDcc/libs/datalibrary/__logging__.ini
tpDcc/libs/datalibrary/__version__.py
tpDcc/libs/datalibrary/_version.py
tpDcc/libs/datalibrary/loader.py
tpDcc/libs/datalibrary/core/__init__.py
tpDcc/libs/datalibrary/core/consts.py
tpDcc/libs/datalibrary/core/datalib.py
tpDcc/libs/datalibrary/core/datapart.py
tpDcc/libs/datalibrary/core/exceptions.py
tpDcc/libs/datalibrary/core/lib.py
tpDcc/libs/datalibrary/core/mirrortable.py
tpDcc/libs/datalibrary/core/scanner.py
tpDcc/libs/datalibrary/core/transfer.py
tpDcc/libs/datalibrary/core/version.py
tpDcc/libs/datalibrary/data/__init__.py
tpDcc/libs/datalibrary/data/explorer.py
tpDcc/libs/datalibrary/data/fbx.py
tpDcc/libs/datalibrary/data/file.py
tpDcc/libs/datalibrary/data/folder.py
tpDcc/libs/datalibrary/data/jpg.py
tpDcc/libs/datalibrary/data/mirrortable.py
tpDcc/libs/datalibrary/data/obj.py
tpDcc/libs/datalibrary/data/png.py
tpDcc/libs/datalibrary/data/python.py
tpDcc/libs/datalibrary/data/text.py
tpDcc/libs/datalibrary/data/transforms.py
tpDcc/libs/datalibrary/dccs/__init__.py
tpDcc/libs/datalibrary/dccs/max/__init__.py
tpDcc/libs/datalibrary/dccs/max/data/__init__.py
tpDcc/libs/datalibrary/dccs/max/data/maxfile.py
tpDcc/libs/datalibrary/dccs/maya/__init__.py
tpDcc/libs/datalibrary/dccs/maya/core/__init__.py
tpDcc/libs/datalibrary/dccs/maya/core/mirrortable.py
tpDcc/libs/datalibrary/dccs/maya/core/pose.py
tpDcc/libs/datalibrary/dccs/maya/core/selectionset.py
tpDcc/libs/datalibrary/dccs/maya/core/transfer.py
tpDcc/libs/datalibrary/dccs/maya/core/utils.py
tpDcc/libs/datalibrary/dccs/maya/data/__init__.py
tpDcc/libs/datalibrary/dccs/maya/data/curve.py
tpDcc/libs/datalibrary/dccs/maya/data/mayaascii.py
tpDcc/libs/datalibrary/dccs/maya/data/mayabinary.py
tpDcc/libs/datalibrary/dccs/maya/data/pose.py
tpDcc_libs_datalibrary.egg-info/PKG-INFO
tpDcc_libs_datalibrary.egg-info/SOURCES.txt
tpDcc_libs_datalibrary.egg-info/dependency_links.txt
tpDcc_libs_datalibrary.egg-info/not-zip-safe
tpDcc_libs_datalibrary.egg-info/requires.txt
tpDcc_libs_datalibrary.egg-info/top_level.txt