Metadata-Version: 2.1
Name: tpDcc-libs-datalibrary
Version: 0.0.1
Summary: Customizable and easy to use data library.
Home-page: https://github.com/tpDcc/tpDcc-libs-datalibrary
Author: Tomas Poveda
Author-email: tpovedatd@gmail.com
License: MIT
Platform: UNKNOWN
Provides-Extra: dev
Provides-Extra: test
